semmy/__init__.py
semmy/py.typed
semmy-2.0.1.dist-info/METADATA
semmy-2.0.1.dist-info/WHEEL
semmy-2.0.1.dist-info/licenses/LICENSE.md
semmy-2.0.1.dist-info/RECORD
