Metadata-Version: 2.4
Name: semmy
Version: 2.0.1
Summary: Semantic versioning made easy for Python
Project-URL: Homepage, https://pypi.org/project/semmy/
Project-URL: Repository, https://github.com/nikoheikkila/semmy
Project-URL: Documentation, https://github.com/nikoheikkila/semmy/blob/main/README.md
Project-URL: Bug Tracker, https://github.com/nikoheikkila/semmy/issues
Project-URL: Discussions, https://github.com/nikoheikkila/semmy/discussions
Author-email: Niko Heikkilä <yo@nikoheikkila.fi>
License: MIT
License-File: LICENSE.md
Classifier: Development Status :: 5 - Production/Stable
Classifier: Intended Audience :: Developers
Classifier: License :: OSI Approved :: MIT License
Classifier: Programming Language :: Python :: 3
Classifier: Programming Language :: Python :: 3.12
Classifier: Programming Language :: Python :: 3.13
Classifier: Topic :: Software Development :: Libraries :: Python Modules
Classifier: Topic :: System :: Software Distribution
Requires-Python: >=3.12
